ft260/__init__.py
ft260-0.1.4.dist-info/METADATA
ft260-0.1.4.dist-info/WHEEL
ft260-0.1.4.dist-info/licenses/LICENSE
ft260-0.1.4.dist-info/RECORD
