Metadata-Version: 2.4
Name: ft260
Version: 0.1.4
Summary:  PyFT260: A Python driver and interface library for FTDI's FT260 I2C, UART, and GPIO functions 
Project-URL: project, https://www.mlab.cz
Project-URL: documentation, https://github.com/MLAB-project/PyFT260
Project-URL: github, https://github.com/MLAB-project/PyFT260
Project-URL: homepage, https://github.com/MLAB-project/PyFT260
Project-URL: issues, https://github.com/MLAB-project/PyFT260/issues
Author-email: Roman Dvorak <dvorakroman@ust.cz>
Maintainer-email: Roman Dvorak <dvorakroman@ust.cz>
License:                     GNU GENERAL PUBLIC LICENSE
License-File: LICENSE
Classifier: Programming Language :: Python :: 3
Classifier: Programming Language :: Python :: 3.6
Classifier: Programming Language :: Python :: 3.7
Classifier: Programming Language :: Python :: 3.8
Classifier: Programming Language :: Python :: 3.9
Classifier: Programming Language :: Python :: 3.10
Requires-Python: >=3.6
Requires-Dist: hidapi
